fastapi_slack.py
fastapi_slack-0.2.3.dist-info/LICENSE
fastapi_slack-0.2.3.dist-info/WHEEL
fastapi_slack-0.2.3.dist-info/METADATA
fastapi_slack-0.2.3.dist-info/RECORD
